{"components_avatar.md":"Dsm22bA_","components_backtop.md":"Dc3GJP_R","components_button.md":"DuQl9Nh6","components_collapse.md":"aujR2Tk7","components_dropdown.md":"BYAO3oUN","components_icon.md":"Dlqsv0mL","components_imgpreview.md":"DveGQET5","components_input.md":"BDcKYgG9","components_message.md":"B1iZNF_f","components_numberanimation.md":"DnVyHSxs","components_select.md":"DkvLHbLK","components_switch.md":"DyQLXykP","components_textscroll.md":"BPFy2QIM","components_tooltip.md":"DlNaAH3f","configmd_all.md":"_rnnPeU1","configmd_install.md":"BEjTn88Q","configmd_special.md":"Dzt4vgXB","configmd_start.md":"1MRBUuEN","index.md":"DKwIfqPF","start.md":"Depury5s"}
